gitlog/__init__.py
gitlog/follow.py
gitlog/lld.py
gitlog/profile.py
gitlog/repo.py
gitlog/urls.py
gitlog/user.py
Gitlog-0.1.0.dist-info/LICENSE
Gitlog-0.1.0.dist-info/METADATA
Gitlog-0.1.0.dist-info/WHEEL
Gitlog-0.1.0.dist-info/top_level.txt
Gitlog-0.1.0.dist-info/RECORD
