Metadata-Version: 2.1
Name: Gitlog
Version: 0.1.0
Summary: Gitlog is a python library to work with @github logs. 📈
Home-page: https://github.com/Amir-Shamsi/Gitlog
Author: Amir Shamsi
Author-email: amirshamsi.github@gmail.com
License: MIT
Download-URL: https://github.com/Amir-Shamsi/Gitlog/archive/refs/tags/0.1.0.tar.gz
Keywords: Github,logs,api,git,followers,followings,profile
Platform: UNKNOWN
Classifier: Development Status :: 3 - Alpha
Classifier: Intended Audience :: Developers
Classifier: Topic :: Software Development :: Build Tools
Classifier: License :: OSI Approved :: MIT License
Classifier: Programming Language :: Python :: 3
Classifier: Programming Language :: Python :: 3.4
Classifier: Programming Language :: Python :: 3.5
Classifier: Programming Language :: Python :: 3.6
Classifier: Programming Language :: Python :: 3.7
Classifier: Programming Language :: Python :: 3.8
Classifier: Programming Language :: Python :: 3.9
Classifier: Programming Language :: Python :: 3.10
Requires: requests
Requires: simplejson
License-File: LICENSE
